paradise/__init__.py
paradise/__version__.py
paradise/run.py
paradise/server.py
paradise/public/favicon.ico
paradise/template/index.html
paradise-0.3.0.dist-info/LICENSE
paradise-0.3.0.dist-info/METADATA
paradise-0.3.0.dist-info/WHEEL
paradise-0.3.0.dist-info/entry_points.txt
paradise-0.3.0.dist-info/top_level.txt
paradise-0.3.0.dist-info/RECORD
